pytalib/__init__.py
pytalib/graph/__init__.py
pytalib/graph/utils.py
pytalib/graph/visibility_graph.py
pytalib/indicators/__init__.py
pytalib/indicators/base.py
pytalib/indicators/momentum.py
pytalib/indicators/trend.py
pytalib/indicators/volatility.py
pytalib/indicators/volume.py
pytalib/test/__init__.py
pytalib/test/test_momentum.py
pytalib/test/test_trend.py
pytalib-0.0.1.dist-info/LICENSE
pytalib-0.0.1.dist-info/METADATA
pytalib-0.0.1.dist-info/WHEEL
pytalib-0.0.1.dist-info/top_level.txt
pytalib-0.0.1.dist-info/RECORD
